cuttlepool.py
cuttlepool-0.9.1.dist-info/LICENSE
cuttlepool-0.9.1.dist-info/METADATA
cuttlepool-0.9.1.dist-info/WHEEL
cuttlepool-0.9.1.dist-info/top_level.txt
cuttlepool-0.9.1.dist-info/RECORD
