Metadata-Version: 2.1
Name: cuttlepool
Version: 0.9.1
Summary: A resource pool implementation
Home-page: https://github.com/smitchell556/cuttlepool
Author: Spencer Mitchell
License: BSD 3-Clause
Keywords: sql connection pool
Platform: UNKNOWN
Classifier: Development Status :: 4 - Beta
Classifier: Intended Audience :: Developers
Classifier: License :: OSI Approved :: BSD License
Classifier: Operating System :: OS Independent
Classifier: Programming Language :: Python :: 2.7
Classifier: Programming Language :: Python :: 3.4
Classifier: Programming Language :: Python :: 3.5
Classifier: Programming Language :: Python :: 3.6
Classifier: Programming Language :: Python :: 3.7
Classifier: Programming Language :: Python :: 3.8
Classifier: Topic :: Software Development :: Libraries :: Python Modules
Provides-Extra: dev
Requires-Dist: pytest ; extra == 'dev'
